Workbook

Sheet RRHH
A1: Rol | B1: Cantidad | C1: Sueldo Mensual | D1: Costo Mensual
A2: Jefe Proyecto | B2: 1 | C2: 800000 | D2: =B2*C2 -> 800000
A3: Arquitecto | B3: 1 | C3: 800000 | D3: =B3*C3 -> 800000
A4: Desarrollador | B4: 1 | C4: 700000 | D4: =B4*C4 -> 700000
A5: QA | B5: 1 | C5: 700000 | D5: =B5*C5 -> 700000
A6: Promotor-DevOps | B6: 1 | C6: 750000 | D6: =B6*C6 -> 750000
A7: DB | B7: 1 | C7: 800000 | D7: =B7*C7 -> 800000
C10: Total mensual | D10: =SUM(D2:D7) -> 4550000
C11: Total anual | D11: =D10*12 -> 54600000
C12: Total con indirectos (30%) | D12: =D11*1.3 -> 70980000
C13: CAJA | D13: 35640000

Sheet Licencias
A1: Concepto | B1: Costo Anual
A2: IDEs Desarrollo VScode | B2: 0
A3: Cloud | B3: 12145440
A4: Testing | B4: 9566539
A5: IDEs PostgreSQL | B5: 0
A6: IDEs Python | B6: 0
A7: VPN Proton Essentials | B7: 1497834.1
A8: Mongo db | B8: 652000
A9: Amazon SES (API correo) | B9: 6749.9
A10: Red Hat Enterprise Linux (RHEL) | B10: 2549603.6
A11: Total Licencias | B11: =SUM(B2:B10) -> 26418167

Sheet Evaluacion
A1: Concepto | B1: Monto CLP
A2: Costo RRHH Total | B2: =RRHH!D12 -> 70980000
A3: Costo Licencias | B3: =Licencias!B11 -> 26418167
A4: Costo Total Proyecto | B4: =B2+B3 -> 97398167
A5: Beneficio mensual | B5: =(RRHH!D10+(Licencias!B11/12)) -> 6751513.9 | C5: Aquí puede ser ahorro HH dado la implementación del sistema
A6: Beneficio anual | B6: =B5*12 -> 81018167
A7: Ganancia | B7: =B6-B4 -> -16380000
A8: Rendimiento | B8: =(B6-B4)/B4 -> -0.16817565

Sheet Rendimiento
A1: Concepto | B1: Monto CLP
A2: Costo RRHH Total | B2: =RRHH!D12 -> 70980000
A3: Costo Licencias | B3: =Licencias!B11 -> 26418167
A4: Costo Total Proyecto | B4: =B2+B3 -> 97398167 | C4: =B4/12 -> 8116513.9
A5: Beneficio mensual | B5: =(RRHH!D10+(Licencias!B11/12)) -> 6751513.9 | C5: Aquí puede ser ahorro HH dado la implementación del sistema
A6: Beneficio anual | B6: =B5*12 -> 81018167
A7: Ganancia | B7: =B6-B4 -> -16380000
A8: Rendimiento | B8: =B6/B4 -> 0.83182435

Sheet EdeCostoyBenef
B1: Periodo 0 | C1: Mes1 | D1: Mes2 | E1: Mes3 | F1: Mes4 | G1: Mes5 | H1: Mes6 | I1: Mes7 | J1: Mes8 | K1: Mes9 | L1: Mes10 | M1: Mes11 | N1: Mes12
A2: Beneficio | C2: 8797181 | D2: 8797181 | E2: 8797181 | F2: 8797181 | G2: 8797181 | H2: 8797181 | I2: 8797181 | J2: 8797181 | K2: 8797181 | L2: 8797181 | M2: 8797181 | N2: 8797181
A3: Costo | C3: 6751514 | D3: 5250000 | E3: 5250000 | F3: 5250000 | G3: 5250000 | H3: 5250000 | I3: 5250000 | J3: 5250000 | K3: 5250000 | L3: 5250000 | M3: 5250000 | N3: 5250000
A4: INVERSION | B4: -23940000 | C4: =C2-C3 -> 2045667 | D4: =D2-D3 -> 3547181 | E4: =E2-E3 -> 3547181 | F4: =F2-F3 -> 3547181 | G4: =G2-G3 -> 3547181 | H4: =H2-H3 -> 3547181 | I4: =I2-I3 -> 3547181 | J4: =J2-J3 -> 3547181 | ... N4: =N2-N3 -> 3547181
A5: La Inversión para el ejemplo corresponde sólo al periodo 0, del mes1 en adelante corresponde a la diferencia entre el beneficio y el costo
A6: Si el i esta dado por el usuario por ejemplo 10% sino calcular CAPM
A8: VAN | B8: {=NPV(0.1,C4:N4)+B4} -> -1135614.6
A9: TIR | B9: =IRR(B4:N4) -> 0.090655655

Sheet EdeCostoyBenefv2
B1: Periodo 0 | C1: Mes1 | D1: Mes2 | E1: Mes3 | F1: Mes4 | G1: Mes5 | H1: Mes6 | I1: Mes7 | J1: Mes8 | K1: Mes9 | L1: Mes10 | M1: Mes11 | N1: Mes12
A2: Beneficio | C2: 8797181 | D2: 8797181 | E2: 8797181 | F2: 8797181 | G2: 8797181 | H2: 8797181 | I2: 8797181 | J2: 8797181 | K2: 8797181 | L2: 8797181 | M2: 8797181 | N2: 8797181
A3: Costo | C3: 6751514 | D3: 6751514 | E3: 6751514 | F3: 6751514 | G3: 6751514 | H3: 6751514 | I3: 6751514 | J3: 6751514 | K3: 6751514 | L3: 6751514 | M3: 6751514 | N3: 6751514
A4: INVERSION | B4: -16599000 | C4: =C2-C3 -> 2045667 | D4: =D2-D3 -> 2045667 | E4: =E2-E3 -> 2045667 | F4: =F2-F3 -> 2045667 | G4: =G2-G3 -> 2045667 | H4: =H2-H3 -> 2045667 | I4: =I2-I3 -> 2045667 | J4: =J2-J3 -> 2045667 | ... N4: =N2-N3 -> 2045667
A5: Flujos Actualizados | B5: -16599000 | C5: =C4/POWER(1.1,1) -> 1859697.3 | D5: =D4/POWER(1.1,2) -> 1690633.9 | E5: =E4/POWER(1.1,3) -> 1536939.9 | F5: =F4/POWER(1.1,4) -> 1397218.1 | G5: =G4/POWER(1.1,5) -> 1270198.3 | H5: =H4/POWER(1.1,6) -> 1154725.7 | I5: =I4/POWER(1.1,7) -> 1049750.6 | J5: =J4/POWER(1.1,8) -> 954318.75 | K5: =K4/POWER(1.1,9) -> 867562.5 | L5: =L4/POWER(1.1,10) -> 788693.18 | M5: =M4/POWER(1.1,11) -> 716993.8 | N5: =N4/POWER(1.1,12) -> 651812.55
A7: La Inversión para el ejemplo corresponde sólo al periodo 0, del mes1 en adelante corresponde a la diferencia entre el beneficio y el costo
A8: Si el i esta dado por el usuario por ejemplo 10% sino calcular CAPM
A10: VAN | B10: {=NPV(0.1,C4:N4)+B4} -> -2660455.5 | D10: =SUM(B5:N5) -> -2660455.5
A11: TIR | B11: =IRR(B4:N4) -> 0.066013307 | D11: =IRR(B4:N4) -> 0.066013307
